{
  "projectRoot": "d:\\SalesAndStockManagement",
  "batchFiles": [
    {"path": "QA_TEST_PLAN.md", "language": "markdown", "sizeLines": 553, "fileCategory": "docs"},
    {"path": "README.md", "language": "markdown", "sizeLines": 113, "fileCategory": "docs"},
    {"path": "analysis_options.yaml", "language": "yaml", "sizeLines": 1, "fileCategory": "config"},
    {"path": "package.json", "language": "json", "sizeLines": 25, "fileCategory": "config"},
    {"path": "pubspec.yaml", "language": "yaml", "sizeLines": 57, "fileCategory": "config"},
    {"path": "recent_logs.txt", "language": "txt", "sizeLines": 200, "fileCategory": "docs"},
    {"path": "tmp2.txt", "language": "txt", "sizeLines": 65, "fileCategory": "docs"}
  ],
  "batchImportData": {"QA_TEST_PLAN.md":[],"README.md":[],"analysis_options.yaml":[],"package.json":[],"pubspec.yaml":[],"recent_logs.txt":[],"tmp2.txt":[]}
}